chap_2/rom.v
module rom(
    input wire ce,
    input wire[5:0] addr,
    output reg [31:0]inst
);
//使用二维向量定义存储器
reg[31:0] rom [63:0];//这段 Verilog 代码描述了一个名为 rom 的数组，它包含 64 个元素，每个元素都是一个 32 位的寄存器（reg[31:0]），表示为 [63:0]
always@(*)begin 
    if(ce==1'b0)begin
        inst<=32'h0;
    end
    else begin
     inst<=rom[addr];
    end
end

endmodule

chap_2/pc_reg.v
module  pc_reg(
    input wire clk,
    input wire rst,
    output reg[5:0] pc,
    output reg ce
);
always @(posedge clk) begin
    if(rst==1'b1)begin
        ce<=1'b0;
    end
    else begin
        ce<='b1;
    end

end
always @(posedge clk) begin
    if(ce==1'b1)begin
        pc<=6'h00; //指令存储器使能信号无效，pc保持0
    end
    else begin
        pc<=pc+1'b1;//pc在每个时钟周期+1
    end
end
    
endmodule

chap_2/inst_fetch.v
module inst_fetch(
    input wire clk,
    input wire rst,
    output [31:0] inst_o
);
wire [5:0]pc;
wire rom_ce;
pc_reg pc_reg0(.clk(clk),.rst(rst),.pc(pc),.ce(rom_ce));
rom rom0(.ce(rom_ce),.addr(pc),.inst(inst_o));

endmodule

chap_2/waveform.vcd
$version Generated by VerilatedVcd $end
$timescale 1ps $end

 $scope module TOP $end
  $var wire  1 # clk $end
  $var wire 32 % inst_o [31:0] $end
  $var wire  1 $ rst $end
  $scope module inst_fetch $end
   $var wire  1 # clk $end
   $var wire 32 % inst_o [31:0] $end
   $var wire  6 & pc [5:0] $end
   $var wire  1 ' rom_ce $end
   $var wire  1 $ rst $end
   $scope module pc_reg0 $end
    $var wire  1 ' ce $end
    $var wire  1 # clk $end
    $var wire  6 & pc [5:0] $end
    $var wire  1 $ rst $end
   $upscope $end
   $scope module rom0 $end
    $var wire  6 & addr [5:0] $end
    $var wire  1 ' ce $end
    $var wire 32 % inst [31:0] $end
   $upscope $end
  $upscope $end
 $upscope $end
$enddefinitions $end


#0
1#
0$
b00000000000000000000000000000000 %
b000000 &
0'
#1
0#
#2
1#
b00010010001101000101011001111000 %
b000001 &
1'
#3
0#
#4
1#
b000000 &
#5
0#
1$
#6
1#
b00000000000000000000000000000000 %
0'
#7
0#
#8
1#
b000001 &
#9
0#
#10
1#
b000010 &
#11
0#
#12
1#
b000011 &
#13
0#
#14
1#
b000100 &
#15
0#
#16
1#
b000101 &
#17
0#
#18
1#
b000110 &
#19
0#
#20
1#
b000111 &
#21
0#
#22
1#
b001000 &
#23
0#
#24
1#
b001001 &
#25
0#
#26
1#
b001010 &
#27
0#
#28
1#
b001011 &
#29
0#
#30
1#
b001100 &
#31
0#
#32
1#
b001101 &
#33
0#
#34
1#
b001110 &
#35
0#
#36
1#
b001111 &
#37
0#
#38
1#
b010000 &
